[
  {
    "ref": "MC43Nz",
    "url": "https://google.fr/",
    "date": "2025-01-12",
    "time": "9:00:30 PM",
    "click": "0"
  },
  {
    "ref": "MC4xND",
    "url": "https://google.fr/test",
    "date": "2025-01-18",
    "time": "21:34:13",
    "click": "0"
  },
  {
    "ref": "MC40NT",
    "url": "https://www.youtube.com/embed/Lwbp9WfLslc?si=WNMUYUd8K7Deziw2",
    "date": "2025-01-19",
    "time": "12:54:59",
    "click": 14527
  },
  {
    "ref": "MC42MT",
    "url": "14524",
    "date": "2025-01-19",
    "time": "1:16:21 PM",
    "click": "0"
  },
  {
    "ref": "MC4zNj",
    "url": "https://short-pi.vercel.app/r.htm?MC40NT",
    "date": "2025-01-19",
    "time": "15:02:45",
    "click": 1
  },
  {
    "ref": "MC43MD",
    "url": "https://high-kora.com/TOD/ch2/test.html?file=https%3A%2F%2Fsps1.starzplayarabia.com%2Fout%2Fv1%2F41ff8fde1cd84ed5b30ab8198755356b%2Findex.mpd&clearkey_keyId=b253c726c24c7c94a3ddf9b1907e2c76&clearkey_key=097963d6ad73c3d712a104981de0ed42",
    "date": "2025-01-19",
    "time": "5:00:50 PM",
    "click": "0"
  }
]